[
  [
    {
      "label": "Address",
      "type": "input",
      "name": "address",
      "elementType": "text",
      "placeholder": "Your Home Address"
    },
    {
      "label": "Phone Number",
      "type": "phonenumber",
      "name": "phonenumber",
      "elementType": "phonenumber",
      "placeholder": "Your Phonenumber"
    }
  ],
  [
    {
      "label": "City",
      "type": "input",
      "name": "city",
      "elementType": "text",
      "placeholder": "City"
    },
    {
      "label": "State",
      "type": "input",
      "name": "state",
      "elementType": "text",
      "placeholder": "State"
    }
  ],
  [
    {
      "label": "Zip",
      "type": "input",
      "name": "zip",
      "elementType": "text",
      "placeholder": "zip"
    },
    {
      "label": "Select Country",
      "type": "country",
      "name": "country",
      "elementType": "text"
    }
  ],
  [
    {
      "label": "Sex",
      "type": "select",
      "name": "sex",
      "elementType": "select",
      "options": [
        { "text": "Select Sex", "value": "" },
        { "text": "Male", "value": "MALE" },
        { "text": "Female", "value": "FEMALE" }
      ]
    },
    {
      "label": "Date of Birth",
      "type": "input",
      "name": "dateOfBirth",
      "elementType": "text",
      "placeholder": "MM/DD/YYYY"
    }
  ]
]
